odoo8_addon_web_list_html_widget-8.0.1.0.0-py2.7-nspkg.pth
odoo8_addon_web_list_html_widget-8.0.1.0.0.dist-info/DESCRIPTION.rst
odoo8_addon_web_list_html_widget-8.0.1.0.0.dist-info/METADATA
odoo8_addon_web_list_html_widget-8.0.1.0.0.dist-info/RECORD
odoo8_addon_web_list_html_widget-8.0.1.0.0.dist-info/WHEEL
odoo8_addon_web_list_html_widget-8.0.1.0.0.dist-info/metadata.json
odoo8_addon_web_list_html_widget-8.0.1.0.0.dist-info/namespace_packages.txt
odoo8_addon_web_list_html_widget-8.0.1.0.0.dist-info/top_level.txt
odoo_addons/web_list_html_widget/README.rst
odoo_addons/web_list_html_widget/__init__.py
odoo_addons/web_list_html_widget/__openerp__.py
odoo_addons/web_list_html_widget/static/description/icon.png
odoo_addons/web_list_html_widget/static/src/js/view_list.js
odoo_addons/web_list_html_widget/views/web_list_html_widget.xml
